pb/__init__.py
pb/main.py
procboss-0.3.1.dist-info/LICENSE.md
procboss-0.3.1.dist-info/METADATA
procboss-0.3.1.dist-info/WHEEL
procboss-0.3.1.dist-info/entry_points.txt
procboss-0.3.1.dist-info/top_level.txt
procboss-0.3.1.dist-info/RECORD
