Metadata-Version: 2.1
Name: procboss
Version: 0.3.1
Summary: A process management tool that lists or kills processes by name and port.
Home-page: https://github.com/ryanraposo/pb
Author: ryanraposo
Author-email: raposo.ryan@gmail.com
Classifier: Programming Language :: Python :: 3
Classifier: License :: OSI Approved :: MIT License
Classifier: Operating System :: OS Independent
Requires-Python: >=3.6
License-File: LICENSE.md
Requires-Dist: tabulate
Requires-Dist: termcolor
